{"title": "Konata", "id": "Konata", "stickers": [{"body": "0+woman_running+\ud83c\udfc3\u200d\u2640\ufe0f", "url": "mxc://matrix.org/YaQsqBmIwSWRUXMEyKJkTfDp", "info": {"w": 256, "h": 255, "size": 176879, "mimetype": "image/png", "thumbnail_url": "mxc://matrix.org/YaQsqBmIwSWRUXMEyKJkTfDp", "thumbnail_info": {"w": 256, "h": 255, "size": 176879, "mimetype": "image/png"}}, "msgtype": "m.sticker", "id": "sha256:abed9674cbc20aff5426a0f602b7230d6becec3aae4e5a332919bc6023d9194e"}, {"body": "1+glass_of_milk+\ud83e\udd5b", "url": "mxc://matrix.org/oVmnLhDIPiGHTGiOMLbIvnuy", "info": {"w": 256, "h": 255, "size": 150333, "mimetype": "image/png", "thumbnail_url": "mxc://matrix.org/oVmnLhDIPiGHTGiOMLbIvnuy", "thumbnail_info": {"w": 256, "h": 255, "size": 150333, "mimetype": "image/png"}}, "msgtype": "m.sticker", "id": "sha256:67842fd6ed7f1b6120545cd5736d91bfcede30d1157bc3710e81bf4f64f76be9"}, {"body": "10+thought_balloon+\ud83d\udcad", "url": "mxc://matrix.org/kOPWDgdHRNXoBRtWPmolTqpc", "info": {"w": 256, "h": 256, "size": 116377, "mimetype": "image/png", "thumbnail_url": "mxc://matrix.org/kOPWDgdHRNXoBRtWPmolTqpc", "thumbnail_info": {"w": 256, "h": 256, "size": 116377, "mimetype": "image/png"}}, "msgtype": "m.sticker", "id": "sha256:6f78d87c9bb897b4a522c67b849de2714aa844c965eed3ba9ef4c7e3297c5e41"}, {"body": "100+grinning_face_with_sweat+\ud83d\ude05", "url": "mxc://matrix.org/tmomiSPAOkpArSkdrnnWmVWA", "info": {"w": 256, "h": 222, "size": 175782, "mimetype": "image/png", "thumbnail_url": "mxc://matrix.org/tmomiSPAOkpArSkdrnnWmVWA", "thumbnail_info": {"w": 256, "h": 222, "size": 175782, "mimetype": "image/png"}}, "msgtype": "m.sticker", "id": "sha256:b75fa7be040f61ee8085080891d7a759fe03b44a6bf179c41377138506bb71ac"}, {"body": "101+squinting_face_with_tongue+\ud83d\ude1d", "url": "mxc://matrix.org/cCDfdgcEzFIjMwzKfHxTosaV", "info": {"w": 256, "h": 254, "size": 250744, "mimetype": "image/png", "thumbnail_url": "mxc://matrix.org/cCDfdgcEzFIjMwzKfHxTosaV", "thumbnail_info": {"w": 256, "h": 254, "size": 250744, "mimetype": "image/png"}}, "msgtype": "m.sticker", "id": "sha256:096da9781866853cea358f42da7fcc19b3f78bf611b1a0cb5b05f24e92bb71ba"}, {"body": "102+running_shoe+\ud83d\udc5f", "url": "mxc://matrix.org/ysYPNbbnyOUaXuhrNSGuBTlg", "info": {"w": 256, "h": 256, "size": 201162, "mimetype": "image/png", "thumbnail_url": "mxc://matrix.org/ysYPNbbnyOUaXuhrNSGuBTlg", "thumbnail_info": {"w": 256, "h": 256, "size": 201162, "mimetype": "image/png"}}, "msgtype": "m.sticker", "id": "sha256:1e7c832df775cb2c1e159b8c2fb57278536cdd3b0c8f39ac0476f431b1628434"}, {"body": "103+unamused_face+\ud83d\ude12", "url": "mxc://matrix.org/NrFsOjNuWVLKoBjHMYzcwryB", "info": {"w": 256, "h": 256, "size": 196100, "mimetype": "image/png", "thumbnail_url": "mxc://matrix.org/NrFsOjNuWVLKoBjHMYzcwryB", "thumbnail_info": {"w": 256, "h": 256, "size": 196100, "mimetype": "image/png"}}, "msgtype": "m.sticker", "id": "sha256:3307507f50bece86891499d76372c66acf82798c214d0234bcb41cebd4ebe10d"}, {"body": "104+face_savoring_food+\ud83d\ude0b", "url": "mxc://matrix.org/WhRAszeQEoFwOEkSAYxsLAFN", "info": {"w": 256, "h": 184, "size": 163159, "mimetype": "image/png", "thumbnail_url": "mxc://matrix.org/WhRAszeQEoFwOEkSAYxsLAFN", "thumbnail_info": {"w": 256, "h": 184, "size": 163159, "mimetype": "image/png"}}, "msgtype": "m.sticker", "id": "sha256:b0aefeb4d4e8c52dc7968256197befa94e7910d29c8768362c6a3246e9bf6ea2"}, {"body": "105+loudly_crying_face+\ud83d\ude2d", "url": "mxc://matrix.org/vsGMQpXKaXtVGFDTniSNOmbM", "info": {"w": 256, "h": 228, "size": 194826, "mimetype": "image/png", "thumbnail_url": "mxc://matrix.org/vsGMQpXKaXtVGFDTniSNOmbM", "thumbnail_info": {"w": 256, "h": 228, "size": 194826, "mimetype": "image/png"}}, "msgtype": "m.sticker", "id": "sha256:27f326c0ffa27b91dc3feafecb19c3916269f9fb2a303eed79d69023e83fdc94"}, {"body": "106+downcast_face_with_sweat+\ud83d\ude13", "url": "mxc://matrix.org/XeNMEikPJjaqVXWMEEEVRjwG", "info": {"w": 255, "h": 256, "size": 133834, "mimetype": "image/png", "thumbnail_url": "mxc://matrix.org/XeNMEikPJjaqVXWMEEEVRjwG", "thumbnail_info": {"w": 255, "h": 256, "size": 133834, "mimetype": "image/png"}}, "msgtype": "m.sticker", "id": "sha256:aca8b4097aa4a80be7c58ec8984aab9907f0c127cc8e2b9bbe09250a31c403ef"}, {"body": "107+sparkles+\u2728", "url": "mxc://matrix.org/rtXThePABkbxySvrmrAjVWAJ", "info": {"w": 256, "h": 227, "size": 176333, "mimetype": "image/png", "thumbnail_url": "mxc://matrix.org/rtXThePABkbxySvrmrAjVWAJ", "thumbnail_info": {"w": 256, "h": 227, "size": 176333, "mimetype": "image/png"}}, "msgtype": "m.sticker", "id": "sha256:099d51f20980437997929acf229d76e3efe2feaeb18a17d0a0ac422c1e227c82"}, {"body": "108+angry_face+\ud83d\ude20", "url": "mxc://matrix.org/wsMAfILEJPzqnarXGczYgSoG", "info": {"w": 256, "h": 239, "size": 95708, "mimetype": "image/png", "thumbnail_url": "mxc://matrix.org/wsMAfILEJPzqnarXGczYgSoG", "thumbnail_info": {"w": 256, "h": 239, "size": 95708, "mimetype": "image/png"}}, "msgtype": "m.sticker", "id": "sha256:8a6edf216aa92c37206762fae672abbc2473bd252075faae75b3f9194bed3546"}, {"body": "109+exclamation_question_mark+\u2049\ufe0f", "url": "mxc://matrix.org/ZbIxhHpyZwpjguvMlhfccJka", "info": {"w": 256, "h": 230, "size": 83344, "mimetype": "image/png", "thumbnail_url": "mxc://matrix.org/ZbIxhHpyZwpjguvMlhfccJka", "thumbnail_info": {"w": 256, "h": 230, "size": 83344, "mimetype": "image/png"}}, "msgtype": "m.sticker", "id": "sha256:267899db73618d0956724391e9d7b994e2890a31834fc80441f874b535799fe2"}, {"body": "11+face_without_mouth+\ud83d\ude36", "url": "mxc://matrix.org/mreKPTkmLZBNXLDRNzlMQOoX", "info": {"w": 256, "h": 180, "size": 158204, "mimetype": "image/png", "thumbnail_url": "mxc://matrix.org/mreKPTkmLZBNXLDRNzlMQOoX", "thumbnail_info": {"w": 256, "h": 180, "size": 158204, "mimetype": "image/png"}}, "msgtype": "m.sticker", "id": "sha256:4d0f90b43ea7300a3f2a225090b7ccb04d31f8a3edb9c21c7557479278b07182"}, {"body": "110+speech_balloon+\ud83d\udcac", "url": "mxc://matrix.org/AqrHwEXziOjTEXSqVILdOHSR", "info": {"w": 256, "h": 247, "size": 88004, "mimetype": "image/png", "thumbnail_url": "mxc://matrix.org/AqrHwEXziOjTEXSqVILdOHSR", "thumbnail_info": {"w": 256, "h": 247, "size": 88004, "mimetype": "image/png"}}, "msgtype": "m.sticker", "id": "sha256:cf48d3c7db9779bc862271d9024354ed8159e5a05b49cfbf7b51cffab6b3eb5c"}, {"body": "111+thinking_face+\ud83e\udd14", "url": "mxc://matrix.org/SwFfOHJpidOHjEEggxOnkFab", "info": {"w": 256, "h": 187, "size": 152204, "mimetype": "image/png", "thumbnail_url": "mxc://matrix.org/SwFfOHJpidOHjEEggxOnkFab", "thumbnail_info": {"w": 256, "h": 187, "size": 152204, "mimetype": "image/png"}}, "msgtype": "m.sticker", "id": "sha256:e6ec641125867cb6fb1377118c1358ec89319dafaadd6906c58049987a9e64a7"}, {"body": "112+speech_balloon+\ud83d\udcac", "url": "mxc://matrix.org/NblFOmGlZzoIsEClXPrYBzoU", "info": {"w": 256, "h": 168, "size": 123475, "mimetype": "image/png", "thumbnail_url": "mxc://matrix.org/NblFOmGlZzoIsEClXPrYBzoU", "thumbnail_info": {"w": 256, "h": 168, "size": 123475, "mimetype": "image/png"}}, "msgtype": "m.sticker", "id": "sha256:83e5b3d47271baca100bfe327fbd951f8772f60cf7b1cd3281d6a55484328f05"}, {"body": "113+man_tipping_hand+\ud83d\udc81\u200d\u2642\ufe0f", "url": "mxc://matrix.org/xxPUjJlKkyBrhWzAWlvpkrTg", "info": {"w": 256, "h": 255, "size": 217301, "mimetype": "image/png", "thumbnail_url": "mxc://matrix.org/xxPUjJlKkyBrhWzAWlvpkrTg", "thumbnail_info": {"w": 256, "h": 255, "size": 217301, "mimetype": "image/png"}}, "msgtype": "m.sticker", "id": "sha256:e5cd79a30da51b89b3f2ed2a288b06397f6ecf9146e0dc248a7dd511b453e1c0"}, {"body": "114+money_with_wings+\ud83d\udcb8", "url": "mxc://matrix.org/DmQuzgBsWcQrtoVhErRHMhmu", "info": {"w": 256, "h": 254, "size": 177720, "mimetype": "image/png", "thumbnail_url": "mxc://matrix.org/DmQuzgBsWcQrtoVhErRHMhmu", "thumbnail_info": {"w": 256, "h": 254, "size": 177720, "mimetype": "image/png"}}, "msgtype": "m.sticker", "id": "sha256:5ac88739d4c45eb2bc1922f76832a2c6d12f789ab4595ff73140bb102ee4cfad"}, {"body": "115+teacup_without_handle+\ud83c\udf75", "url": "mxc://matrix.org/AjDOyRNswNJhEwFfLcmahmBA", "info": {"w": 256, "h": 254, "size": 170012, "mimetype": "image/png", "thumbnail_url": "mxc://matrix.org/AjDOyRNswNJhEwFfLcmahmBA", "thumbnail_info": {"w": 256, "h": 254, "size": 170012, "mimetype": "image/png"}}, "msgtype": "m.sticker", "id": "sha256:018239d580c2c395ce3966528a56eae181a26870494958b2d7dd0ab2db2a8e86"}, {"body": "116+rainbow+\ud83c\udf08", "url": "mxc://matrix.org/UnrZIEjqtCQRjVdQCGmhYtJh", "info": {"w": 256, "h": 218, "size": 143761, "mimetype": "image/png", "thumbnail_url": "mxc://matrix.org/UnrZIEjqtCQRjVdQCGmhYtJh", "thumbnail_info": {"w": 256, "h": 218, "size": 143761, "mimetype": "image/png"}}, "msgtype": "m.sticker", "id": "sha256:974cd451130b56b2e326e9d6e2874fcaad3d93ff70c0a18ac4a99e2b1eaed4f6"}, {"body": "117+thumbs_up+\ud83d\udc4d", "url": "mxc://matrix.org/hOxvQhbUHfjYnEwfOIdPmOuB", "info": {"w": 256, "h": 149, "size": 154340, "mimetype": "image/png", "thumbnail_url": "mxc://matrix.org/hOxvQhbUHfjYnEwfOIdPmOuB", "thumbnail_info": {"w": 256, "h": 149, "size": 154340, "mimetype": "image/png"}}, "msgtype": "m.sticker", "id": "sha256:661d14cab8f533c5b9da99d84e72fa77b673b89c7bb3b6bb07ac49c311c285e9"}, {"body": "118+face_without_mouth+\ud83d\ude36", "url": "mxc://matrix.org/UwBlEJqeGjqrIfxWOfSoAxIn", "info": {"w": 255, "h": 256, "size": 165346, "mimetype": "image/png", "thumbnail_url": "mxc://matrix.org/UwBlEJqeGjqrIfxWOfSoAxIn", "thumbnail_info": {"w": 255, "h": 256, "size": 165346, "mimetype": "image/png"}}, "msgtype": "m.sticker", "id": "sha256:9b86c49cbd82cd17a6f3b42392358ec9dc775a206db7494c7a1887fc23949452"}, {"body": "119+loudly_crying_face+\ud83d\ude2d", "url": "mxc://matrix.org/XPTkiQqDNPTqsuaEyYOtFGAd", "info": {"w": 256, "h": 204, "size": 149898, "mimetype": "image/png", "thumbnail_url": "mxc://matrix.org/XPTkiQqDNPTqsuaEyYOtFGAd", "thumbnail_info": {"w": 256, "h": 204, "size": 149898, "mimetype": "image/png"}}, "msgtype": "m.sticker", "id": "sha256:cdb3af73a6857049f634ae62f7d746e3ce9aecb7534cfa1c5214cec62b105094"}, {"body": "12+smirking_face+\ud83d\ude0f", "url": "mxc://matrix.org/xHboXRZdtlGXjnHxIBzkXlEt", "info": {"w": 256, "h": 256, "size": 151705, "mimetype": "image/png", "thumbnail_url": "mxc://matrix.org/xHboXRZdtlGXjnHxIBzkXlEt", "thumbnail_info": {"w": 256, "h": 256, "size": 151705, "mimetype": "image/png"}}, "msgtype": "m.sticker", "id": "sha256:846d77d59891a012571f6dacb2e4d6ec0a498d8a2de1a8b577bbc0fd85f0710f"}, {"body": "13+desktop_computer+\ud83d\udda5", "url": "mxc://matrix.org/PccTLaOEYnOwoUGRnnThIxzz", "info": {"w": 256, "h": 255, "size": 179327, "mimetype": "image/png", "thumbnail_url": "mxc://matrix.org/PccTLaOEYnOwoUGRnnThIxzz", "thumbnail_info": {"w": 256, "h": 255, "size": 179327, "mimetype": "image/png"}}, "msgtype": "m.sticker", "id": "sha256:b30569cc09ebc07cf3d3ed3574ae9af615857d15ab39665379233f91167cca28"}, {"body": "14+grinning_face_with_sweat+\ud83d\ude05", "url": "mxc://matrix.org/WwpitUvmvDuReYyyDyhnTLHr", "info": {"w": 256, "h": 255, "size": 201689, "mimetype": "image/png", "thumbnail_url": "mxc://matrix.org/WwpitUvmvDuReYyyDyhnTLHr", "thumbnail_info": {"w": 256, "h": 255, "size": 201689, "mimetype": "image/png"}}, "msgtype": "m.sticker", "id": "sha256:c4d59e006e88fef604a96204671d2198f3299eb7b7823951eae70e8dba09a1dc"}, {"body": "15+expressionless_face+\ud83d\ude11", "url": "mxc://matrix.org/uRQBTqUikAPrlQoJgedCgcwB", "info": {"w": 256, "h": 155, "size": 109970, "mimetype": "image/png", "thumbnail_url": "mxc://matrix.org/uRQBTqUikAPrlQoJgedCgcwB", "thumbnail_info": {"w": 256, "h": 155, "size": 109970, "mimetype": "image/png"}}, "msgtype": "m.sticker", "id": "sha256:0a2270eb40685d6c8bdadd10dcd9df36c0eada6b0021c3d39e0cd88c3e34691e"}, {"body": "16+red_question_mark+\u2753", "url": "mxc://matrix.org/pdKsWRtyzPtEtoyztwmGxhat", "info": {"w": 256, "h": 256, "size": 141630, "mimetype": "image/png", "thumbnail_url": "mxc://matrix.org/pdKsWRtyzPtEtoyztwmGxhat", "thumbnail_info": {"w": 256, "h": 256, "size": 141630, "mimetype": "image/png"}}, "msgtype": "m.sticker", "id": "sha256:89f75af885bed7f6f1b2c347eaf76e934fed64a84894a6d7badd755a4e8d2803"}, {"body": "17+smiling_face_with_horns+\ud83d\ude08", "url": "mxc://matrix.org/jiKlOCDKKFaFqgynrSyXrpII", "info": {"w": 256, "h": 256, "size": 174360, "mimetype": "image/png", "thumbnail_url": "mxc://matrix.org/jiKlOCDKKFaFqgynrSyXrpII", "thumbnail_info": {"w": 256, "h": 256, "size": 174360, "mimetype": "image/png"}}, "msgtype": "m.sticker", "id": "sha256:f5856c657e3b5272d3b6de62ccbcdb3d844d0368fc7f6202efd67aa69d4bda05"}, {"body": "18+thinking_face+\ud83e\udd14", "url": "mxc://matrix.org/nKOOXhVulEuNjIdpdZijBvst", "info": {"w": 256, "h": 255, "size": 221474, "mimetype": "image/png", "thumbnail_url": "mxc://matrix.org/nKOOXhVulEuNjIdpdZijBvst", "thumbnail_info": {"w": 256, "h": 255, "size": 221474, "mimetype": "image/png"}}, "msgtype": "m.sticker", "id": "sha256:40b7ecd28082621ed8f4a9ac99e84d44f6073e361f28ec36960f7d60ef4a60f3"}, {"body": "19+confused_face+\ud83d\ude15", "url": "mxc://matrix.org/zgobJXQoKuIvJWFElPHgdHkY", "info": {"w": 256, "h": 143, "size": 109081, "mimetype": "image/png", "thumbnail_url": "mxc://matrix.org/zgobJXQoKuIvJWFElPHgdHkY", "thumbnail_info": {"w": 256, "h": 143, "size": 109081, "mimetype": "image/png"}}, "msgtype": "m.sticker", "id": "sha256:5e198b6ebd6772a385448249ab5f2fb5601bcf4a6abea7a2da476451247d156f"}, {"body": "2+expressionless_face+\ud83d\ude11", "url": "mxc://matrix.org/dbSLKGYEmXjXJxYPhjLcsDue", "info": {"w": 256, "h": 256, "size": 178881, "mimetype": "image/png", "thumbnail_url": "mxc://matrix.org/dbSLKGYEmXjXJxYPhjLcsDue", "thumbnail_info": {"w": 256, "h": 256, "size": 178881, "mimetype": "image/png"}}, "msgtype": "m.sticker", "id": "sha256:a1249e2ffcf55d9c2e51e77b2d8cc126e6335a26ad1ca829b889a3a74fbb6f7d"}, {"body": "20+thinking_face+\ud83e\udd14", "url": "mxc://matrix.org/MmwjYdwIyaRphLEJFrhDqyIo", "info": {"w": 256, "h": 255, "size": 202098, "mimetype": "image/png", "thumbnail_url": "mxc://matrix.org/MmwjYdwIyaRphLEJFrhDqyIo", "thumbnail_info": {"w": 256, "h": 255, "size": 202098, "mimetype": "image/png"}}, "msgtype": "m.sticker", "id": "sha256:73c7851eb142f708d474532e4bfcf4ead6e3980922437ba15a212b6643ff45aa"}, {"body": "21+face_with_tears_of_joy+\ud83d\ude02", "url": "mxc://matrix.org/vbKEBodnAxdhXynwIaCYqhQs", "info": {"w": 256, "h": 256, "size": 172342, "mimetype": "image/png", "thumbnail_url": "mxc://matrix.org/vbKEBodnAxdhXynwIaCYqhQs", "thumbnail_info": {"w": 256, "h": 256, "size": 172342, "mimetype": "image/png"}}, "msgtype": "m.sticker", "id": "sha256:2280cd8789058c9ee2b8f2d34a07b3166137e6825f145136791433cc9934c90c"}, {"body": "22+smiling_face+\u263a\ufe0f", "url": "mxc://matrix.org/OLuCBeuAHwSgFbvSGoaSoycm", "info": {"w": 256, "h": 256, "size": 166808, "mimetype": "image/png", "thumbnail_url": "mxc://matrix.org/OLuCBeuAHwSgFbvSGoaSoycm", "thumbnail_info": {"w": 256, "h": 256, "size": 166808, "mimetype": "image/png"}}, "msgtype": "m.sticker", "id": "sha256:7cbacabbd49ef201e4f8a8837c42041b08cf7be5e4dd72a29337779c61d9eb34"}, {"body": "23+smiling_face_with_halo+\ud83d\ude07", "url": "mxc://matrix.org/ooOQamvIbACGFzRTGhBaChhs", "info": {"w": 256, "h": 255, "size": 176320, "mimetype": "image/png", "thumbnail_url": "mxc://matrix.org/ooOQamvIbACGFzRTGhBaChhs", "thumbnail_info": {"w": 256, "h": 255, "size": 176320, "mimetype": "image/png"}}, "msgtype": "m.sticker", "id": "sha256:f57037278702ad203d27b40ac16615424259ca4bd557d54fc219f78be1c8a7e8"}, {"body": "24+index_pointing_up+\u261d\ufe0f", "url": "mxc://matrix.org/xYzStJKRIBgDlAsityPAdyNi", "info": {"w": 256, "h": 255, "size": 220818, "mimetype": "image/png", "thumbnail_url": "mxc://matrix.org/xYzStJKRIBgDlAsityPAdyNi", "thumbnail_info": {"w": 256, "h": 255, "size": 220818, "mimetype": "image/png"}}, "msgtype": "m.sticker", "id": "sha256:d41e9d316d221d8ba43e3588e20405f350aaaf10043101e6668ad70b0a67e541"}, {"body": "25+fork_and_knife_with_plate+\ud83c\udf7d", "url": "mxc://matrix.org/RmPNPPZhpEAujbvlNyRflcsW", "info": {"w": 256, "h": 256, "size": 161523, "mimetype": "image/png", "thumbnail_url": "mxc://matrix.org/RmPNPPZhpEAujbvlNyRflcsW", "thumbnail_info": {"w": 256, "h": 256, "size": 161523, "mimetype": "image/png"}}, "msgtype": "m.sticker", "id": "sha256:172b7c2a95b25162dc791ccfde6f72182ea4fb3ebb75cd1ece18f8a3da801a19"}, {"body": "26+telescope+\ud83d\udd2d", "url": "mxc://matrix.org/fIIwXYPQdvltPouYlLBQZtFd", "info": {"w": 256, "h": 256, "size": 184763, "mimetype": "image/png", "thumbnail_url": "mxc://matrix.org/fIIwXYPQdvltPouYlLBQZtFd", "thumbnail_info": {"w": 256, "h": 256, "size": 184763, "mimetype": "image/png"}}, "msgtype": "m.sticker", "id": "sha256:e13879f2d054f8ed6cd98bf693526b64f6fd5408682c08c97b0708b1e15a1ea7"}, {"body": "27+open_book+\ud83d\udcd6", "url": "mxc://matrix.org/MKiGxoXhDBAQyrFAcnBBtzbV", "info": {"w": 256, "h": 200, "size": 195931, "mimetype": "image/png", "thumbnail_url": "mxc://matrix.org/MKiGxoXhDBAQyrFAcnBBtzbV", "thumbnail_info": {"w": 256, "h": 200, "size": 195931, "mimetype": "image/png"}}, "msgtype": "m.sticker", "id": "sha256:de7b17c0200b365ec95b9a54a4475f3466d40214ccb0b83a082d727447cd15b3"}, {"body": "28+person_tipping_hand+\ud83d\udc81", "url": "mxc://matrix.org/pcRzaEYiqjGdJXDIzEyXgSXU", "info": {"w": 256, "h": 157, "size": 138108, "mimetype": "image/png", "thumbnail_url": "mxc://matrix.org/pcRzaEYiqjGdJXDIzEyXgSXU", "thumbnail_info": {"w": 256, "h": 157, "size": 138108, "mimetype": "image/png"}}, "msgtype": "m.sticker", "id": "sha256:25f6932b02b0d64342c269b05f37e860c1f6364d5ca6d1967c42196e90aa4de0"}, {"body": "29+victory_hand+\u270c\ufe0f", "url": "mxc://matrix.org/ljEEGnUJzDBnYjaJnZsetfom", "info": {"w": 256, "h": 255, "size": 217007, "mimetype": "image/png", "thumbnail_url": "mxc://matrix.org/ljEEGnUJzDBnYjaJnZsetfom", "thumbnail_info": {"w": 256, "h": 255, "size": 217007, "mimetype": "image/png"}}, "msgtype": "m.sticker", "id": "sha256:218f10ac7153ba4cc20d203ca196f38a15fea9873c122b8773db35894739569a"}, {"body": "3+face_without_mouth+\ud83d\ude36", "url": "mxc://matrix.org/zuMODukQqVuRobivWYvaDoKd", "info": {"w": 256, "h": 256, "size": 152602, "mimetype": "image/png", "thumbnail_url": "mxc://matrix.org/zuMODukQqVuRobivWYvaDoKd", "thumbnail_info": {"w": 256, "h": 256, "size": 152602, "mimetype": "image/png"}}, "msgtype": "m.sticker", "id": "sha256:3035cf7ed75a0a173752701249563432dec71131fb7e1ae53e2717305d5ed571"}, {"body": "30+video_game+\ud83c\udfae", "url": "mxc://matrix.org/QNcersrlCpoUlsVtYSqOuzBo", "info": {"w": 256, "h": 256, "size": 148380, "mimetype": "image/png", "thumbnail_url": "mxc://matrix.org/QNcersrlCpoUlsVtYSqOuzBo", "thumbnail_info": {"w": 256, "h": 256, "size": 148380, "mimetype": "image/png"}}, "msgtype": "m.sticker", "id": "sha256:2af77a025e2eb4a186790e603ccc8630b5502152738d18e59039bc30ce17a20f"}, {"body": "31+thinking_face+\ud83e\udd14", "url": "mxc://matrix.org/RNymHiywgrPtasPkvOUsnEVq", "info": {"w": 256, "h": 255, "size": 201735, "mimetype": "image/png", "thumbnail_url": "mxc://matrix.org/RNymHiywgrPtasPkvOUsnEVq", "thumbnail_info": {"w": 256, "h": 255, "size": 201735, "mimetype": "image/png"}}, "msgtype": "m.sticker", "id": "sha256:ddd61ae9982ffe0a23ccc54f75b0dc5fca8de13914693b80ada4246e2d43c564"}, {"body": "32+tongue+\ud83d\udc45", "url": "mxc://matrix.org/AXHNKhlrFUKGuVntqiQkvHVx", "info": {"w": 256, "h": 255, "size": 122651, "mimetype": "image/png", "thumbnail_url": "mxc://matrix.org/AXHNKhlrFUKGuVntqiQkvHVx", "thumbnail_info": {"w": 256, "h": 255, "size": 122651, "mimetype": "image/png"}}, "msgtype": "m.sticker", "id": "sha256:b04fdf7a86ab8682f35ccbfeb23511cec8f6e700eb95db0b93a036bd8ac312ab"}, {"body": "33+unamused_face+\ud83d\ude12", "url": "mxc://matrix.org/NomCwhfXwTKqKctDGKmMFkwm", "info": {"w": 256, "h": 256, "size": 202392, "mimetype": "image/png", "thumbnail_url": "mxc://matrix.org/NomCwhfXwTKqKctDGKmMFkwm", "thumbnail_info": {"w": 256, "h": 256, "size": 202392, "mimetype": "image/png"}}, "msgtype": "m.sticker", "id": "sha256:04772e8e5c7acf28510e3eeb979987dbcfaa388319cb3a5ddb7f7f516e2b44a0"}, {"body": "34+winking_face+\ud83d\ude09", "url": "mxc://matrix.org/AYfkQiCnoKAHMipPefgxjQUF", "info": {"w": 256, "h": 256, "size": 185293, "mimetype": "image/png", "thumbnail_url": "mxc://matrix.org/AYfkQiCnoKAHMipPefgxjQUF", "thumbnail_info": {"w": 256, "h": 256, "size": 185293, "mimetype": "image/png"}}, "msgtype": "m.sticker", "id": "sha256:e7afa1efa559c8f5bf63df8a334b5b177aea73919ded325546a9ff76c2e4f516"}, {"body": "35+thumbs_up+\ud83d\udc4d", "url": "mxc://matrix.org/yUnMhdrsDPpenngvfnPvybjx", "info": {"w": 256, "h": 256, "size": 243037, "mimetype": "image/png", "thumbnail_url": "mxc://matrix.org/yUnMhdrsDPpenngvfnPvybjx", "thumbnail_info": {"w": 256, "h": 256, "size": 243037, "mimetype": "image/png"}}, "msgtype": "m.sticker", "id": "sha256:e8e55bc3145ad14bca70f7be2d902ce4663454efe732de2cabee51ada40554dc"}, {"body": "36+sleepy_face+\ud83d\ude2a", "url": "mxc://matrix.org/EKWAlhOTeFMvuMXUglBCeNhh", "info": {"w": 256, "h": 255, "size": 193102, "mimetype": "image/png", "thumbnail_url": "mxc://matrix.org/EKWAlhOTeFMvuMXUglBCeNhh", "thumbnail_info": {"w": 256, "h": 255, "size": 193102, "mimetype": "image/png"}}, "msgtype": "m.sticker", "id": "sha256:80d57f9bc1c297d1b98f9d572d0625c47cff4076942253f4071c3f3ff83cd0ad"}, {"body": "37+sleepy_face+\ud83d\ude2a", "url": "mxc://matrix.org/RicEOuTOZvNrIRfqngRVFHVl", "info": {"w": 256, "h": 256, "size": 181785, "mimetype": "image/png", "thumbnail_url": "mxc://matrix.org/RicEOuTOZvNrIRfqngRVFHVl", "thumbnail_info": {"w": 256, "h": 256, "size": 181785, "mimetype": "image/png"}}, "msgtype": "m.sticker", "id": "sha256:4acc20e0ad6f9b156b84ad4aa72839191eb4a481fe307579d933218218dfcd83"}, {"body": "38+person_gesturing_NO+\ud83d\ude45", "url": "mxc://matrix.org/xLkXMEaDCEfvIwCFHYggRviz", "info": {"w": 256, "h": 256, "size": 190860, "mimetype": "image/png", "thumbnail_url": "mxc://matrix.org/xLkXMEaDCEfvIwCFHYggRviz", "thumbnail_info": {"w": 256, "h": 256, "size": 190860, "mimetype": "image/png"}}, "msgtype": "m.sticker", "id": "sha256:84dab82257f0bfe94b61a3700fa54e027e305f2e0c41de9aab2694947a840c04"}, {"body": "39+downcast_face_with_sweat+\ud83d\ude13", "url": "mxc://matrix.org/CLYDClavLVCBaTqXmEEvuTAX", "info": {"w": 256, "h": 256, "size": 176845, "mimetype": "image/png", "thumbnail_url": "mxc://matrix.org/CLYDClavLVCBaTqXmEEvuTAX", "thumbnail_info": {"w": 256, "h": 256, "size": 176845, "mimetype": "image/png"}}, "msgtype": "m.sticker", "id": "sha256:638e308d0fed1a037660eb99d593657c4f8891b63b33210e9bfa1dcbe0cecae1"}, {"body": "4+speech_balloon+\ud83d\udcac", "url": "mxc://matrix.org/vFfupkILsMSqSsPCNqvEaBZH", "info": {"w": 256, "h": 256, "size": 93529, "mimetype": "image/png", "thumbnail_url": "mxc://matrix.org/vFfupkILsMSqSsPCNqvEaBZH", "thumbnail_info": {"w": 256, "h": 256, "size": 93529, "mimetype": "image/png"}}, "msgtype": "m.sticker", "id": "sha256:8677386fb379342e71f7234a1b6154e9f582269d21f166ea00fe22e3d553e58e"}, {"body": "40+light_bulb+\ud83d\udca1", "url": "mxc://matrix.org/anWLgNKhTzakPisBJCPIEixk", "info": {"w": 256, "h": 255, "size": 224982, "mimetype": "image/png", "thumbnail_url": "mxc://matrix.org/anWLgNKhTzakPisBJCPIEixk", "thumbnail_info": {"w": 256, "h": 255, "size": 224982, "mimetype": "image/png"}}, "msgtype": "m.sticker", "id": "sha256:2aae2865a6f5372a0c48c2d573bfb22eba1e1f432e9dcdc2fde4c7e7f20332d4"}, {"body": "41+raised_hand+\u270b\ufe0f", "url": "mxc://matrix.org/EypgcQtvJYFePaDRMYlbLlaH", "info": {"w": 256, "h": 256, "size": 195473, "mimetype": "image/png", "thumbnail_url": "mxc://matrix.org/EypgcQtvJYFePaDRMYlbLlaH", "thumbnail_info": {"w": 256, "h": 256, "size": 195473, "mimetype": "image/png"}}, "msgtype": "m.sticker", "id": "sha256:ddf56e393bf402d43981e9ecff1825c3b95e388d1df047c8a56c6937481f16a0"}, {"body": "42+open_hands+\ud83d\udc50", "url": "mxc://matrix.org/CjFxQKMhSWJsJfjVTZxIPVoA", "info": {"w": 256, "h": 256, "size": 196705, "mimetype": "image/png", "thumbnail_url": "mxc://matrix.org/CjFxQKMhSWJsJfjVTZxIPVoA", "thumbnail_info": {"w": 256, "h": 256, "size": 196705, "mimetype": "image/png"}}, "msgtype": "m.sticker", "id": "sha256:430c9b542e0d367cabea8bb524a65fe2cca591471750fbc38f71bbefe207fef0"}, {"body": "43+sun+\u2600\ufe0f", "url": "mxc://matrix.org/XucuWXmYbeYjQlLChQFJVphR", "info": {"w": 256, "h": 255, "size": 472108, "mimetype": "image/png", "thumbnail_url": "mxc://matrix.org/XucuWXmYbeYjQlLChQFJVphR", "thumbnail_info": {"w": 256, "h": 255, "size": 472108, "mimetype": "image/png"}}, "msgtype": "m.sticker", "id": "sha256:8871a154eff3a6bd61e11beb8f83a926656ce3e9cb1cdd5cc143996143930506"}, {"body": "44+kissing_face+\ud83d\ude17", "url": "mxc://matrix.org/fxYFjaeFBiaAhLdapAbWgejn", "info": {"w": 256, "h": 256, "size": 173153, "mimetype": "image/png", "thumbnail_url": "mxc://matrix.org/fxYFjaeFBiaAhLdapAbWgejn", "thumbnail_info": {"w": 256, "h": 256, "size": 173153, "mimetype": "image/png"}}, "msgtype": "m.sticker", "id": "sha256:1d367c4675eefc169a548cbe69cca59c82030646ec3b64a0ac27f3b95811aa71"}, {"body": "45+worried_face+\ud83d\ude1f", "url": "mxc://matrix.org/pRKmLoTahfBddGKcVITXMXpY", "info": {"w": 256, "h": 256, "size": 199881, "mimetype": "image/png", "thumbnail_url": "mxc://matrix.org/pRKmLoTahfBddGKcVITXMXpY", "thumbnail_info": {"w": 256, "h": 256, "size": 199881, "mimetype": "image/png"}}, "msgtype": "m.sticker", "id": "sha256:4f16c902baa939f368f1d830b57194b5f98eb6a94f6e7113c750a255dd8883da"}, {"body": "46+face_savoring_food+\ud83d\ude0b", "url": "mxc://matrix.org/xzIuNjNKdAEOWscOjrQFwZRV", "info": {"w": 256, "h": 255, "size": 132181, "mimetype": "image/png", "thumbnail_url": "mxc://matrix.org/xzIuNjNKdAEOWscOjrQFwZRV", "thumbnail_info": {"w": 256, "h": 255, "size": 132181, "mimetype": "image/png"}}, "msgtype": "m.sticker", "id": "sha256:7e667792003ba1395b3e323ac0cebe2634128f670918fbaba25ec47ac39a62b3"}, {"body": "47+eye+\ud83d\udc41", "url": "mxc://matrix.org/WSKFOcrhCWVEZKGvQdulEyuN", "info": {"w": 256, "h": 154, "size": 129948, "mimetype": "image/png", "thumbnail_url": "mxc://matrix.org/WSKFOcrhCWVEZKGvQdulEyuN", "thumbnail_info": {"w": 256, "h": 154, "size": 129948, "mimetype": "image/png"}}, "msgtype": "m.sticker", "id": "sha256:2662669fed623049a8e914e0ae409cf64f1e15ea5d51d16b12f053db202b3a60"}, {"body": "48+oncoming_fist+\ud83d\udc4a", "url": "mxc://matrix.org/bLjWIuhaihcONlDqluKxZcwj", "info": {"w": 256, "h": 204, "size": 231248, "mimetype": "image/png", "thumbnail_url": "mxc://matrix.org/bLjWIuhaihcONlDqluKxZcwj", "thumbnail_info": {"w": 256, "h": 204, "size": 231248, "mimetype": "image/png"}}, "msgtype": "m.sticker", "id": "sha256:e79d66242be0be573447ca8bb4fd4825b4c7e088bd1f0e059f4b252228179514"}, {"body": "49+relieved_face+\ud83d\ude0c", "url": "mxc://matrix.org/lMTXoxKUJXKQevnRFgCJTytB", "info": {"w": 256, "h": 255, "size": 160324, "mimetype": "image/png", "thumbnail_url": "mxc://matrix.org/lMTXoxKUJXKQevnRFgCJTytB", "thumbnail_info": {"w": 256, "h": 255, "size": 160324, "mimetype": "image/png"}}, "msgtype": "m.sticker", "id": "sha256:bb2ca8338413b04a5481284f7ed9d054542cb043a4073d013fe8bf572c7e889a"}, {"body": "5+index_pointing_up+\u261d\ufe0f", "url": "mxc://matrix.org/gtfvTAwFpvRXbIbzDYKkqfnX", "info": {"w": 256, "h": 144, "size": 135397, "mimetype": "image/png", "thumbnail_url": "mxc://matrix.org/gtfvTAwFpvRXbIbzDYKkqfnX", "thumbnail_info": {"w": 256, "h": 144, "size": 135397, "mimetype": "image/png"}}, "msgtype": "m.sticker", "id": "sha256:50516687b6cec6fb773ac3ddf422fe5b148ed4ecc85ecbb19071b0a277c9fb39"}, {"body": "50+dashing_away+\ud83d\udca8", "url": "mxc://matrix.org/YFJTaKpvoxjZxYxxRHGSPKwr", "info": {"w": 256, "h": 255, "size": 198085, "mimetype": "image/png", "thumbnail_url": "mxc://matrix.org/YFJTaKpvoxjZxYxxRHGSPKwr", "thumbnail_info": {"w": 256, "h": 255, "size": 198085, "mimetype": "image/png"}}, "msgtype": "m.sticker", "id": "sha256:e05d447959a55317e65bf5deb27f22a88867dc91e5d19d2320569a7a8b62dba8"}, {"body": "51+anxious_face_with_sweat+\ud83d\ude30", "url": "mxc://matrix.org/kycfYzyDbkToviDxqfPxVbse", "info": {"w": 256, "h": 255, "size": 189367, "mimetype": "image/png", "thumbnail_url": "mxc://matrix.org/kycfYzyDbkToviDxqfPxVbse", "thumbnail_info": {"w": 256, "h": 255, "size": 189367, "mimetype": "image/png"}}, "msgtype": "m.sticker", "id": "sha256:3b7eccb0903bec8f1b7a892cded03a631773258799864f974f4d02767eaf729e"}, {"body": "52+weary_face+\ud83d\ude29", "url": "mxc://matrix.org/xcJdJaAzPFKSXOLJxGHjpELF", "info": {"w": 256, "h": 255, "size": 230618, "mimetype": "image/png", "thumbnail_url": "mxc://matrix.org/xcJdJaAzPFKSXOLJxGHjpELF", "thumbnail_info": {"w": 256, "h": 255, "size": 230618, "mimetype": "image/png"}}, "msgtype": "m.sticker", "id": "sha256:ccd7c7a83cd4ed8d713e7a7b4cce7613f628899bf1df87ebb8ffc54b0cb7798f"}, {"body": "53+confused_face+\ud83d\ude15", "url": "mxc://matrix.org/KfkByadAIjFpqabMuwmcgwvm", "info": {"w": 256, "h": 255, "size": 138775, "mimetype": "image/png", "thumbnail_url": "mxc://matrix.org/KfkByadAIjFpqabMuwmcgwvm", "thumbnail_info": {"w": 256, "h": 255, "size": 138775, "mimetype": "image/png"}}, "msgtype": "m.sticker", "id": "sha256:0fa476e76667aa4ca98b8c5bf410b96423d1a2fcaedaeb1e82d7c593eecce8fd"}, {"body": "54+water_pistol+\ud83d\udd2b", "url": "mxc://matrix.org/zaYdgiYrEkIhMurcvJfAKATD", "info": {"w": 256, "h": 256, "size": 203710, "mimetype": "image/png", "thumbnail_url": "mxc://matrix.org/zaYdgiYrEkIhMurcvJfAKATD", "thumbnail_info": {"w": 256, "h": 256, "size": 203710, "mimetype": "image/png"}}, "msgtype": "m.sticker", "id": "sha256:fa9f894a19959215b375376f09dca1517000759ac276e03cb04691e18b0c573e"}, {"body": "55+face_with_crossed-out_eyes+\ud83d\ude35", "url": "mxc://matrix.org/aZnaESEaGTQmcJwUdxFscFnU", "info": {"w": 256, "h": 255, "size": 206057, "mimetype": "image/png", "thumbnail_url": "mxc://matrix.org/aZnaESEaGTQmcJwUdxFscFnU", "thumbnail_info": {"w": 256, "h": 255, "size": 206057, "mimetype": "image/png"}}, "msgtype": "m.sticker", "id": "sha256:d55e7c213f688cb0b9af3086b84e5dd0a7bca2f76a2fab60046a53268790df9c"}, {"body": "56+tornado+\ud83c\udf2a", "url": "mxc://matrix.org/nxBBFmOkXtwMeYOAOXeMqxFT", "info": {"w": 256, "h": 143, "size": 113452, "mimetype": "image/png", "thumbnail_url": "mxc://matrix.org/nxBBFmOkXtwMeYOAOXeMqxFT", "thumbnail_info": {"w": 256, "h": 143, "size": 113452, "mimetype": "image/png"}}, "msgtype": "m.sticker", "id": "sha256:32de57f26592bbc7277fb1de61e6b2e76d02f56173edd3723191d10b1477e00b"}, {"body": "57+confounded_face+\ud83d\ude16", "url": "mxc://matrix.org/EQpjfRCnHLfRGIddyEFhznVH", "info": {"w": 256, "h": 131, "size": 143842, "mimetype": "image/png", "thumbnail_url": "mxc://matrix.org/EQpjfRCnHLfRGIddyEFhznVH", "thumbnail_info": {"w": 256, "h": 131, "size": 143842, "mimetype": "image/png"}}, "msgtype": "m.sticker", "id": "sha256:1fe238c64a8be803af67b3321e71bf6e55b87e53924fd13bdb3aa5e8da414f9f"}, {"body": "58+tired_face+\ud83d\ude2b", "url": "mxc://matrix.org/oGQLrbHLdNziboFVQudGqhYb", "info": {"w": 256, "h": 189, "size": 196204, "mimetype": "image/png", "thumbnail_url": "mxc://matrix.org/oGQLrbHLdNziboFVQudGqhYb", "thumbnail_info": {"w": 256, "h": 189, "size": 196204, "mimetype": "image/png"}}, "msgtype": "m.sticker", "id": "sha256:bcf2a39443b7de64859fd5009c631b1377fb4bd3089bb1e6c6f5d9ea2378b635"}, {"body": "59+slightly_frowning_face+\ud83d\ude41", "url": "mxc://matrix.org/YOXvBHTGFriBLngHgfcuvjdB", "info": {"w": 256, "h": 164, "size": 154353, "mimetype": "image/png", "thumbnail_url": "mxc://matrix.org/YOXvBHTGFriBLngHgfcuvjdB", "thumbnail_info": {"w": 256, "h": 164, "size": 154353, "mimetype": "image/png"}}, "msgtype": "m.sticker", "id": "sha256:1af8718b0c4cd4999273a339f8d0b8971fcba78f549f6fd5893460a369ca7d69"}, {"body": "6+grinning_face+\ud83d\ude00", "url": "mxc://matrix.org/AMRpiquwHJBocrVUhtwmGPdB", "info": {"w": 256, "h": 255, "size": 212647, "mimetype": "image/png", "thumbnail_url": "mxc://matrix.org/AMRpiquwHJBocrVUhtwmGPdB", "thumbnail_info": {"w": 256, "h": 255, "size": 212647, "mimetype": "image/png"}}, "msgtype": "m.sticker", "id": "sha256:d98146d23c699ce670bc7c4fb79fd9d9d8fb282128c40a883d2593f14f44f197"}, {"body": "60+grinning_squinting_face+\ud83d\ude06", "url": "mxc://matrix.org/AxbttwzxHPvwxNrTGQkkohwn", "info": {"w": 256, "h": 255, "size": 200594, "mimetype": "image/png", "thumbnail_url": "mxc://matrix.org/AxbttwzxHPvwxNrTGQkkohwn", "thumbnail_info": {"w": 256, "h": 255, "size": 200594, "mimetype": "image/png"}}, "msgtype": "m.sticker", "id": "sha256:8165e2ef0f5b08d77e32db0fc583cf9c4aa795fff99693339d4cf57dbbddcbaf"}, {"body": "61+face_screaming_in_fear+\ud83d\ude31", "url": "mxc://matrix.org/zySoJMhfGzKAXnkKoHgvjvhB", "info": {"w": 256, "h": 256, "size": 310135, "mimetype": "image/png", "thumbnail_url": "mxc://matrix.org/zySoJMhfGzKAXnkKoHgvjvhB", "thumbnail_info": {"w": 256, "h": 256, "size": 310135, "mimetype": "image/png"}}, "msgtype": "m.sticker", "id": "sha256:7694d732e4579feb389347d42c14b5c9178dcc1956bbc46f01dc87c81e6b8b77"}, {"body": "62+slightly_smiling_face+\ud83d\ude42", "url": "mxc://matrix.org/mqtiLSXDNxviTsfknIfsytWK", "info": {"w": 256, "h": 256, "size": 232085, "mimetype": "image/png", "thumbnail_url": "mxc://matrix.org/mqtiLSXDNxviTsfknIfsytWK", "thumbnail_info": {"w": 256, "h": 256, "size": 232085, "mimetype": "image/png"}}, "msgtype": "m.sticker", "id": "sha256:8db9fa56a342d8a07206423d0d91c59a13b48dfbf367fbb892cb906f2d90c063"}, {"body": "63+backhand_index_pointing_right+\ud83d\udc49", "url": "mxc://matrix.org/zAsOvcXYxKnksmQYCSdoORnC", "info": {"w": 256, "h": 255, "size": 174551, "mimetype": "image/png", "thumbnail_url": "mxc://matrix.org/zAsOvcXYxKnksmQYCSdoORnC", "thumbnail_info": {"w": 256, "h": 255, "size": 174551, "mimetype": "image/png"}}, "msgtype": "m.sticker", "id": "sha256:237e3bb12002ba6cc300c17357286b127029c8f5231dcfd04648693d9e6be156"}, {"body": "64+curry_rice+\ud83c\udf5b", "url": "mxc://matrix.org/XJlZiKEDCzRlIISBHDmLkCMo", "info": {"w": 256, "h": 150, "size": 111448, "mimetype": "image/png", "thumbnail_url": "mxc://matrix.org/XJlZiKEDCzRlIISBHDmLkCMo", "thumbnail_info": {"w": 256, "h": 150, "size": 111448, "mimetype": "image/png"}}, "msgtype": "m.sticker", "id": "sha256:4ac950563a9c91bfbc8af62a407b5366487797a371023f3ab52a139d577b21b4"}, {"body": "65+raised_fist+\u270a\ufe0f", "url": "mxc://matrix.org/olzpUPVcjCpJJlLTCITggFam", "info": {"w": 256, "h": 255, "size": 284146, "mimetype": "image/png", "thumbnail_url": "mxc://matrix.org/olzpUPVcjCpJJlLTCITggFam", "thumbnail_info": {"w": 256, "h": 255, "size": 284146, "mimetype": "image/png"}}, "msgtype": "m.sticker", "id": "sha256:e03260c8d6631fa0e39766f7d32f95c3363b97f32bbf73193981c423db837b6a"}, {"body": "66+smirking_face+\ud83d\ude0f", "url": "mxc://matrix.org/bgWMruqwrpXTEYhAkjvoEGxC", "info": {"w": 256, "h": 256, "size": 195236, "mimetype": "image/png", "thumbnail_url": "mxc://matrix.org/bgWMruqwrpXTEYhAkjvoEGxC", "thumbnail_info": {"w": 256, "h": 256, "size": 195236, "mimetype": "image/png"}}, "msgtype": "m.sticker", "id": "sha256:851d77a2350dafbc432974a86e1f2de3d762752835ae3140cd6281af454c261d"}, {"body": "67+frowning_face_with_open_mouth+\ud83d\ude26", "url": "mxc://matrix.org/rzxOySOtsCbjQTPSevWTsPFv", "info": {"w": 256, "h": 161, "size": 194581, "mimetype": "image/png", "thumbnail_url": "mxc://matrix.org/rzxOySOtsCbjQTPSevWTsPFv", "thumbnail_info": {"w": 256, "h": 161, "size": 194581, "mimetype": "image/png"}}, "msgtype": "m.sticker", "id": "sha256:1e30832cb3ccc774a641fbf9497953cea90a7beb5531fdbb213a2b70f99b12a3"}, {"body": "68+crying_face+\ud83d\ude22", "url": "mxc://matrix.org/ccGnJIGkaNiVwQHDsVQoEQEf", "info": {"w": 256, "h": 256, "size": 217857, "mimetype": "image/png", "thumbnail_url": "mxc://matrix.org/ccGnJIGkaNiVwQHDsVQoEQEf", "thumbnail_info": {"w": 256, "h": 256, "size": 217857, "mimetype": "image/png"}}, "msgtype": "m.sticker", "id": "sha256:4ff97049f65cfc7884dd04a55adbc15ae57d06a2a460ec0741c7fa6d94ece54e"}, {"body": "69+squinting_face_with_tongue+\ud83d\ude1d", "url": "mxc://matrix.org/eLfeaQqcwTKPupavdgXQgqvw", "info": {"w": 256, "h": 256, "size": 174431, "mimetype": "image/png", "thumbnail_url": "mxc://matrix.org/eLfeaQqcwTKPupavdgXQgqvw", "thumbnail_info": {"w": 256, "h": 256, "size": 174431, "mimetype": "image/png"}}, "msgtype": "m.sticker", "id": "sha256:eff19cc99524339938648ed1baca0909f992ea535d15c214d168621e38c8e22c"}, {"body": "7+smiling_face_with_heart-eyes+\ud83d\ude0d", "url": "mxc://matrix.org/jQgpMtWNeIHFKSTgygaXnMzd", "info": {"w": 256, "h": 256, "size": 168083, "mimetype": "image/png", "thumbnail_url": "mxc://matrix.org/jQgpMtWNeIHFKSTgygaXnMzd", "thumbnail_info": {"w": 256, "h": 256, "size": 168083, "mimetype": "image/png"}}, "msgtype": "m.sticker", "id": "sha256:fc60bece68d2cfbfeb314a0f684c83c5f6bc3cda4533fb766c0339e32b5419ff"}, {"body": "70+grinning_face+\ud83d\ude00", "url": "mxc://matrix.org/yMiyTgdwIUcjJJvdoKdKWGYF", "info": {"w": 256, "h": 256, "size": 215227, "mimetype": "image/png", "thumbnail_url": "mxc://matrix.org/yMiyTgdwIUcjJJvdoKdKWGYF", "thumbnail_info": {"w": 256, "h": 256, "size": 215227, "mimetype": "image/png"}}, "msgtype": "m.sticker", "id": "sha256:a53a5cc142ba6aa820ad306800ec9de8964ec5328693f7cbb14fdce192e4104a"}, {"body": "71+grinning_face_with_big_eyes+\ud83d\ude03", "url": "mxc://matrix.org/eWFVnyuRolkYBCRwpfEDKtQE", "info": {"w": 256, "h": 255, "size": 207526, "mimetype": "image/png", "thumbnail_url": "mxc://matrix.org/eWFVnyuRolkYBCRwpfEDKtQE", "thumbnail_info": {"w": 256, "h": 255, "size": 207526, "mimetype": "image/png"}}, "msgtype": "m.sticker", "id": "sha256:428d9c9bc4f0af6cf773a4359462840a9edd9790fa494362803f30260fe24912"}, {"body": "72+anguished_face+\ud83d\ude27", "url": "mxc://matrix.org/ckDsoIcLUJUWplxLrEOGdnxy", "info": {"w": 256, "h": 255, "size": 201043, "mimetype": "image/png", "thumbnail_url": "mxc://matrix.org/ckDsoIcLUJUWplxLrEOGdnxy", "thumbnail_info": {"w": 256, "h": 255, "size": 201043, "mimetype": "image/png"}}, "msgtype": "m.sticker", "id": "sha256:0f0e76a312c2e6b25f3705c37953cb0f2b93adace9d68658aeac4cde801a6b98"}, {"body": "73+sleeping_face+\ud83d\ude34", "url": "mxc://matrix.org/gcTnplxJYwsVkCeoVzBRqSfo", "info": {"w": 256, "h": 255, "size": 226677, "mimetype": "image/png", "thumbnail_url": "mxc://matrix.org/gcTnplxJYwsVkCeoVzBRqSfo", "thumbnail_info": {"w": 256, "h": 255, "size": 226677, "mimetype": "image/png"}}, "msgtype": "m.sticker", "id": "sha256:2e76684682fe56ee1cf82023531eaebd3f3b8c1929e5e7f131da8661bd40498d"}, {"body": "74+sunrise+\ud83c\udf05", "url": "mxc://matrix.org/nLXIRBvvMHYwbvCkcsqcTFIJ", "info": {"w": 256, "h": 151, "size": 127107, "mimetype": "image/png", "thumbnail_url": "mxc://matrix.org/nLXIRBvvMHYwbvCkcsqcTFIJ", "thumbnail_info": {"w": 256, "h": 151, "size": 127107, "mimetype": "image/png"}}, "msgtype": "m.sticker", "id": "sha256:664fe9a9316cbfa7b38153c4ee3239c4b9b3e22c5358edd5cd4dee0eb4adbd3f"}, {"body": "75+disappointed_face+\ud83d\ude1e", "url": "mxc://matrix.org/GkoLRwrAwFZXMlnVjdRVwSXw", "info": {"w": 256, "h": 149, "size": 170933, "mimetype": "image/png", "thumbnail_url": "mxc://matrix.org/GkoLRwrAwFZXMlnVjdRVwSXw", "thumbnail_info": {"w": 256, "h": 149, "size": 170933, "mimetype": "image/png"}}, "msgtype": "m.sticker", "id": "sha256:3b1f04984ebec5be5c4f33d77fcac7864ff5338013b8f95ee44243c639fd3d57"}, {"body": "76+grinning_face_with_sweat+\ud83d\ude05", "url": "mxc://matrix.org/qYIdyIBxKLqLFtftAMCMAyhO", "info": {"w": 256, "h": 217, "size": 148348, "mimetype": "image/png", "thumbnail_url": "mxc://matrix.org/qYIdyIBxKLqLFtftAMCMAyhO", "thumbnail_info": {"w": 256, "h": 217, "size": 148348, "mimetype": "image/png"}}, "msgtype": "m.sticker", "id": "sha256:dd14d6fae0dc5fcef88b1d05221aaaf84219442698ffe588fee6923e8188576c"}, {"body": "77+confused_face+\ud83d\ude15", "url": "mxc://matrix.org/ONRkBYgOJwduxEyASPqONWUN", "info": {"w": 256, "h": 255, "size": 206416, "mimetype": "image/png", "thumbnail_url": "mxc://matrix.org/ONRkBYgOJwduxEyASPqONWUN", "thumbnail_info": {"w": 256, "h": 255, "size": 206416, "mimetype": "image/png"}}, "msgtype": "m.sticker", "id": "sha256:4867131744852ae6f2d6df67ace8d776db2dd23efc3e8ca2e467fd9acb3f6635"}, {"body": "78+frowning_face+\u2639\ufe0f", "url": "mxc://matrix.org/VmbaSrHygaYciznjmJdpOmzC", "info": {"w": 256, "h": 143, "size": 132277, "mimetype": "image/png", "thumbnail_url": "mxc://matrix.org/VmbaSrHygaYciznjmJdpOmzC", "thumbnail_info": {"w": 256, "h": 143, "size": 132277, "mimetype": "image/png"}}, "msgtype": "m.sticker", "id": "sha256:9a7b6bc73248ad5420401c5182590cb768014a14b1130418c34bd830868fd0fa"}, {"body": "79+red_question_mark+\u2753", "url": "mxc://matrix.org/vhnOSyQHsYcVWMayPRGuVVAz", "info": {"w": 256, "h": 240, "size": 180570, "mimetype": "image/png", "thumbnail_url": "mxc://matrix.org/vhnOSyQHsYcVWMayPRGuVVAz", "thumbnail_info": {"w": 256, "h": 240, "size": 180570, "mimetype": "image/png"}}, "msgtype": "m.sticker", "id": "sha256:cb0b255b44692c6efbc6454c70ceb4c62b2a6c2d84442c3904ade8666eeffcd2"}, {"body": "8+disappointed_face+\ud83d\ude1e", "url": "mxc://matrix.org/JmLwpxDKwObzWcncKBdZrqQY", "info": {"w": 256, "h": 255, "size": 180814, "mimetype": "image/png", "thumbnail_url": "mxc://matrix.org/JmLwpxDKwObzWcncKBdZrqQY", "thumbnail_info": {"w": 256, "h": 255, "size": 180814, "mimetype": "image/png"}}, "msgtype": "m.sticker", "id": "sha256:2409bafbb5eab25de90acf4b3e6ada281203c9e412b401e2e16d99f57a2ee031"}, {"body": "80+star+\u2b50\ufe0f", "url": "mxc://matrix.org/fQjrEoPzGzUXFQpabSYfrUIY", "info": {"w": 256, "h": 255, "size": 164292, "mimetype": "image/png", "thumbnail_url": "mxc://matrix.org/fQjrEoPzGzUXFQpabSYfrUIY", "thumbnail_info": {"w": 256, "h": 255, "size": 164292, "mimetype": "image/png"}}, "msgtype": "m.sticker", "id": "sha256:98e05a049b1015be05bb3371655a8cfc904d8237a314c940a6ffe097f30457df"}, {"body": "81+sparkles+\u2728", "url": "mxc://matrix.org/oCkqsLVtcxpHBhLAYAHvyoxp", "info": {"w": 256, "h": 144, "size": 158588, "mimetype": "image/png", "thumbnail_url": "mxc://matrix.org/oCkqsLVtcxpHBhLAYAHvyoxp", "thumbnail_info": {"w": 256, "h": 144, "size": 158588, "mimetype": "image/png"}}, "msgtype": "m.sticker", "id": "sha256:de666fa5a7aee8ee08f8bf6ae749d99af7d20df3b45f0dd115df151aa0727cc5"}, {"body": "82+grinning_squinting_face+\ud83d\ude06", "url": "mxc://matrix.org/pOUwkRsknuvbvxYVKLpTNBJc", "info": {"w": 256, "h": 143, "size": 208897, "mimetype": "image/png", "thumbnail_url": "mxc://matrix.org/pOUwkRsknuvbvxYVKLpTNBJc", "thumbnail_info": {"w": 256, "h": 143, "size": 208897, "mimetype": "image/png"}}, "msgtype": "m.sticker", "id": "sha256:44b51838b497ec40e1766bf40039d102977154404147034da31cc18a4998976b"}, {"body": "83+cherry_blossom+\ud83c\udf38", "url": "mxc://matrix.org/dPPnWxJayTzMeDxMGwmwcyCo", "info": {"w": 256, "h": 256, "size": 210889, "mimetype": "image/png", "thumbnail_url": "mxc://matrix.org/dPPnWxJayTzMeDxMGwmwcyCo", "thumbnail_info": {"w": 256, "h": 256, "size": 210889, "mimetype": "image/png"}}, "msgtype": "m.sticker", "id": "sha256:ed4442e1395f20377c65e4e128754d13d197a8e387da0d0c77cac577c468abda"}, {"body": "84+confused_face+\ud83d\ude15", "url": "mxc://matrix.org/MsbnPidICwKTsXCbZbePqFgD", "info": {"w": 256, "h": 199, "size": 133433, "mimetype": "image/png", "thumbnail_url": "mxc://matrix.org/MsbnPidICwKTsXCbZbePqFgD", "thumbnail_info": {"w": 256, "h": 199, "size": 133433, "mimetype": "image/png"}}, "msgtype": "m.sticker", "id": "sha256:75c61d756dc423ddee3ac8825a0bf62360f53a20f1f44d5872be1c9f9305d9d2"}, {"body": "85+person_tipping_hand+\ud83d\udc81", "url": "mxc://matrix.org/xfAcYwtLVKWneOOMUeDnKhma", "info": {"w": 256, "h": 256, "size": 171504, "mimetype": "image/png", "thumbnail_url": "mxc://matrix.org/xfAcYwtLVKWneOOMUeDnKhma", "thumbnail_info": {"w": 256, "h": 256, "size": 171504, "mimetype": "image/png"}}, "msgtype": "m.sticker", "id": "sha256:9ddbb91756b662f437e6fdf5050e01364c7e429502722a50de4736c79caab38d"}, {"body": "86+index_pointing_up+\u261d\ufe0f", "url": "mxc://matrix.org/GFhCImFIRZdMlZFKfxBJJvkX", "info": {"w": 256, "h": 143, "size": 132806, "mimetype": "image/png", "thumbnail_url": "mxc://matrix.org/GFhCImFIRZdMlZFKfxBJJvkX", "thumbnail_info": {"w": 256, "h": 143, "size": 132806, "mimetype": "image/png"}}, "msgtype": "m.sticker", "id": "sha256:82a74ffd6fe89c11316d652c9c10bb3c2ace48e0dc0744f9bba4cd64ee6d4a5d"}, {"body": "87+fearful_face+\ud83d\ude28", "url": "mxc://matrix.org/wOnJzDlEIQQNIoTRpPxiqPTT", "info": {"w": 256, "h": 256, "size": 222678, "mimetype": "image/png", "thumbnail_url": "mxc://matrix.org/wOnJzDlEIQQNIoTRpPxiqPTT", "thumbnail_info": {"w": 256, "h": 256, "size": 222678, "mimetype": "image/png"}}, "msgtype": "m.sticker", "id": "sha256:55d7d454b18bf5318a206bc8f2bbff97f515a57acc9dd8f790e928a1461a677f"}, {"body": "88+loudly_crying_face+\ud83d\ude2d", "url": "mxc://matrix.org/ZVDPVHssCsCtNKMcCeynpDBg", "info": {"w": 256, "h": 159, "size": 106697, "mimetype": "image/png", "thumbnail_url": "mxc://matrix.org/ZVDPVHssCsCtNKMcCeynpDBg", "thumbnail_info": {"w": 256, "h": 159, "size": 106697, "mimetype": "image/png"}}, "msgtype": "m.sticker", "id": "sha256:89ea73cbd64280e30aee84f087b1b79eff43d145eae5eab8e907d27ff7d13d43"}, {"body": "89+grinning_face_with_smiling_eyes+\ud83d\ude04", "url": "mxc://matrix.org/DecjKebIDIKCDoqKAJAzswVG", "info": {"w": 256, "h": 167, "size": 112957, "mimetype": "image/png", "thumbnail_url": "mxc://matrix.org/DecjKebIDIKCDoqKAJAzswVG", "thumbnail_info": {"w": 256, "h": 167, "size": 112957, "mimetype": "image/png"}}, "msgtype": "m.sticker", "id": "sha256:bbb0a77cb539ebb2a99b351008e646262a5714f34cec34bf92068eb7631494c0"}, {"body": "9+kissing_face+\ud83d\ude17", "url": "mxc://matrix.org/ubOFXTOWQauqgMKbURRCLYzY", "info": {"w": 256, "h": 256, "size": 207986, "mimetype": "image/png", "thumbnail_url": "mxc://matrix.org/ubOFXTOWQauqgMKbURRCLYzY", "thumbnail_info": {"w": 256, "h": 256, "size": 207986, "mimetype": "image/png"}}, "msgtype": "m.sticker", "id": "sha256:2ab7003eb399f90895618cf924575fd43651caf91e159f36ad88cbf8dcdbcd9a"}, {"body": "90+smirking_face+\ud83d\ude0f", "url": "mxc://matrix.org/yMNfleZFVtMYWTRzYUyMguwq", "info": {"w": 256, "h": 255, "size": 235175, "mimetype": "image/png", "thumbnail_url": "mxc://matrix.org/yMNfleZFVtMYWTRzYUyMguwq", "thumbnail_info": {"w": 256, "h": 255, "size": 235175, "mimetype": "image/png"}}, "msgtype": "m.sticker", "id": "sha256:e05256101332402a370652256db1aa21e6c19d410c0993e09fe416d76a805ed3"}, {"body": "91+video_game+\ud83c\udfae", "url": "mxc://matrix.org/CWeqGcHTQfzQlHAlZtpyajNA", "info": {"w": 256, "h": 256, "size": 146402, "mimetype": "image/png", "thumbnail_url": "mxc://matrix.org/CWeqGcHTQfzQlHAlZtpyajNA", "thumbnail_info": {"w": 256, "h": 256, "size": 146402, "mimetype": "image/png"}}, "msgtype": "m.sticker", "id": "sha256:98e3f1e6a6fe64ed3152399d1e7246bc8c33bf6987c2b6401ffd65373ae65ac0"}, {"body": "92+beaming_face_with_smiling_eyes+\ud83d\ude01", "url": "mxc://matrix.org/sxsGwJdPQLMeXXpPTPPwcbUo", "info": {"w": 256, "h": 256, "size": 138835, "mimetype": "image/png", "thumbnail_url": "mxc://matrix.org/sxsGwJdPQLMeXXpPTPPwcbUo", "thumbnail_info": {"w": 256, "h": 256, "size": 138835, "mimetype": "image/png"}}, "msgtype": "m.sticker", "id": "sha256:d937ac2e026a08845dfe7aee12d3a8c7e3bc39bec0c1c9d233c359396250f521"}, {"body": "93+kitchen_knife+\ud83d\udd2a", "url": "mxc://matrix.org/wAjRnAKPjacvJNCuqWDIoZIP", "info": {"w": 256, "h": 232, "size": 141891, "mimetype": "image/png", "thumbnail_url": "mxc://matrix.org/wAjRnAKPjacvJNCuqWDIoZIP", "thumbnail_info": {"w": 256, "h": 232, "size": 141891, "mimetype": "image/png"}}, "msgtype": "m.sticker", "id": "sha256:371a72323739a04c64564cfa9b105d6cdd2b207e6d47642bcb5136dcb80da6af"}, {"body": "94+expressionless_face+\ud83d\ude11", "url": "mxc://matrix.org/JHEEZLLjuLkwcMBzMjBhCjMl", "info": {"w": 256, "h": 256, "size": 150018, "mimetype": "image/png", "thumbnail_url": "mxc://matrix.org/JHEEZLLjuLkwcMBzMjBhCjMl", "thumbnail_info": {"w": 256, "h": 256, "size": 150018, "mimetype": "image/png"}}, "msgtype": "m.sticker", "id": "sha256:58dbff8e7fb3991224aae6b161405cb871a35991fe3515c19a9795a946eadf08"}, {"body": "95+light_bulb+\ud83d\udca1", "url": "mxc://matrix.org/xwFjNfdjrTKoWJDyTZAYiknu", "info": {"w": 256, "h": 199, "size": 170703, "mimetype": "image/png", "thumbnail_url": "mxc://matrix.org/xwFjNfdjrTKoWJDyTZAYiknu", "thumbnail_info": {"w": 256, "h": 199, "size": 170703, "mimetype": "image/png"}}, "msgtype": "m.sticker", "id": "sha256:421deb12768db02eb7b592e3d962396509888e1554a859bc5da591aad0af20df"}, {"body": "96+red_heart+\u2764\ufe0f", "url": "mxc://matrix.org/fRLmxGbDNUWUrjdWsEusULbt", "info": {"w": 256, "h": 256, "size": 168768, "mimetype": "image/png", "thumbnail_url": "mxc://matrix.org/fRLmxGbDNUWUrjdWsEusULbt", "thumbnail_info": {"w": 256, "h": 256, "size": 168768, "mimetype": "image/png"}}, "msgtype": "m.sticker", "id": "sha256:c1d39525e8ed2adf3544276f2fc67d82a5bdebea587ca5e9662026e0e0da6828"}, {"body": "97+red_heart+\u2764\ufe0f", "url": "mxc://matrix.org/mQAAadGgiuaaXZXWSJnLXnWt", "info": {"w": 256, "h": 256, "size": 154572, "mimetype": "image/png", "thumbnail_url": "mxc://matrix.org/mQAAadGgiuaaXZXWSJnLXnWt", "thumbnail_info": {"w": 256, "h": 256, "size": 154572, "mimetype": "image/png"}}, "msgtype": "m.sticker", "id": "sha256:c608ef2188356f318f7565f12c4f668a41f777ab33da0fe2071a43f80830351a"}, {"body": "98+backhand_index_pointing_left+\ud83d\udc48", "url": "mxc://matrix.org/hAJsRDsvosnqBAdwFvEdXvOF", "info": {"w": 256, "h": 255, "size": 82206, "mimetype": "image/png", "thumbnail_url": "mxc://matrix.org/hAJsRDsvosnqBAdwFvEdXvOF", "thumbnail_info": {"w": 256, "h": 255, "size": 82206, "mimetype": "image/png"}}, "msgtype": "m.sticker", "id": "sha256:5b3f15c2f59833b74ba5ea4986c71ba65e7daac948ebba59dacb3131c6fcda2f"}, {"body": "99+speaking_head+\ud83d\udde3", "url": "mxc://matrix.org/WlUcLwHRxPRVqfOgwboGLNXY", "info": {"w": 256, "h": 174, "size": 165879, "mimetype": "image/png", "thumbnail_url": "mxc://matrix.org/WlUcLwHRxPRVqfOgwboGLNXY", "thumbnail_info": {"w": 256, "h": 174, "size": 165879, "mimetype": "image/png"}}, "msgtype": "m.sticker", "id": "sha256:04d95df3520d79a9166c44c311f33f6280acf4fee37cb1458ff73397f3d286cf"}]}